shell_whiz/ai/__init__.py
shell_whiz/ai/client.py
shell_whiz/ai/errors.py
shell_whiz/ai/prompts/edit_shell_command.yml
shell_whiz/ai/prompts/explain_shell_command.yml
shell_whiz/ai/prompts/recognise_dangerous_command.yml
shell_whiz/ai/prompts/suggest_shell_command.yml
shell_whiz/ai/providers/api.py
shell_whiz/ai/providers/openai.py
shell_whiz/cli/__init__.py
shell_whiz/cli/commands/ask.py
shell_whiz/cli/commands/config.py
shell_whiz/cli/commands/explain.py
shell_whiz/cli/core/shell_command.py
shell_whiz/config.py
shell_whiz/main.py
shell_whiz-3.2.6.dist-info/LICENSE
shell_whiz-3.2.6.dist-info/METADATA
shell_whiz-3.2.6.dist-info/WHEEL
shell_whiz-3.2.6.dist-info/entry_points.txt
shell_whiz-3.2.6.dist-info/RECORD
