Metadata-Version: 2.1
Name: shell-whiz
Version: 3.2.6
Summary: AI assistant for command line
Home-page: https://github.com/beyimjan/shell-whiz
License: GPL-3.0-only
Author: Tamerlan Temirbolatuly
Author-email: beyimjan@gmail.com
Requires-Python: >=3.9,<4
Classifier: License :: OSI Approved :: GNU General Public License v3 (GPLv3)
Classifier: Programming Language :: Python :: 3
Classifier: Programming Language :: Python :: 3.9
Classifier: Programming Language :: Python :: 3.10
Classifier: Programming Language :: Python :: 3.11
Classifier: Programming Language :: Python :: 3.12
Requires-Dist: jsonschema (>=4.21.1,<5.0.0)
Requires-Dist: openai (>=1.13.3,<2.0.0)
Requires-Dist: pydantic (>=2.6.3,<3.0.0)
Requires-Dist: pyyaml (>=6.0.1,<7.0.0)
Requires-Dist: questionary (>=2.0.1,<3.0.0)
Requires-Dist: rich (>=13.7.1,<14.0.0)
Requires-Dist: typer[all] (>=0.9.0,<0.10.0)
Requires-Dist: types-jsonschema (>=4.21.0.20240311,<5.0.0.0)
Requires-Dist: types-pyyaml (>=6.0.12.20240311,<7.0.0.0)
Project-URL: Repository, https://github.com/beyimjan/shell-whiz
